tests/classes/__init__.py
tests/classes/test_cls_dict.py
tests/classes/test_cls_function.py
tests/classes/test_literal_meta.py
tests/classes/test_something.py
tests/classes/test_subscribtable_type.py
tests/decorators/__init__.py
tests/decorators/test_hintable.py
tests/functions/__init__.py
tests/functions/test_common_ancestor.py
tests/functions/test_get_args_and_return_type.py
tests/functions/test_get_mro.py
tests/functions/test_get_type.py
tests/functions/test_get_type_hints_of_callable.py
tests/functions/test_instance_of.py
tests/functions/test_is_optional_type.py
tests/functions/test_is_type_annotation.py
tests/functions/test_origin_and_alias.py
tests/functions/test_subclass_of.py
tests/resources/__init__.py
tests/resources/some_module.py
typish/__init__.py
typish/_classes.py
typish/_decorators.py
typish/_functions.py
typish/_meta.py
typish/_state.py
typish/_types.py
typish/effe.py
typish/classes/__init__.py
typish/classes/_cls_dict.py
typish/classes/_cls_function.py
typish/classes/_literal.py
typish/classes/_something.py
typish/classes/_subscriptable_type.py
typish/classes/_union_type.py
typish/decorators/__init__.py
typish/decorators/_hintable.py
typish/functions/__init__.py
typish/functions/_common_ancestor.py
typish/functions/_get_alias.py
typish/functions/_get_args.py
typish/functions/_get_mro.py
typish/functions/_get_origin.py
typish/functions/_get_simple_name.py
typish/functions/_get_type.py
typish/functions/_get_type_hints_of_callable.py
typish/functions/_instance_of.py
typish/functions/_is_from_typing.py
typish/functions/_is_optional_type.py
typish/functions/_is_type_annotation.py
typish/functions/_subclass_of.py
typish-1.9.0.dist-info/LICENSE
typish-1.9.0.dist-info/METADATA
typish-1.9.0.dist-info/WHEEL
typish-1.9.0.dist-info/top_level.txt
typish-1.9.0.dist-info/RECORD
